federated_language/__init__.py
federated_language/version.py
federated_language/common_libs/__init__.py
federated_language/common_libs/async_utils.py
federated_language/common_libs/py_typecheck.py
federated_language/common_libs/retrying.py
federated_language/common_libs/serializable.py
federated_language/common_libs/structure.py
federated_language/common_libs/tracing.py
federated_language/compiler/__init__.py
federated_language/compiler/array.py
federated_language/compiler/building_block_analysis.py
federated_language/compiler/building_block_factory.py
federated_language/compiler/building_blocks.py
federated_language/compiler/intrinsic_defs.py
federated_language/compiler/transformation_utils.py
federated_language/compiler/tree_analysis.py
federated_language/computation/__init__.py
federated_language/computation/computation_analysis.py
federated_language/computation/computation_base.py
federated_language/computation/computation_impl.py
federated_language/computation/computation_wrapper.py
federated_language/computation/function_utils.py
federated_language/computation/polymorphic_computation.py
federated_language/context_stack/__init__.py
federated_language/context_stack/context.py
federated_language/context_stack/context_stack_impl.py
federated_language/context_stack/context_stack_test_utils.py
federated_language/context_stack/runtime_error_context.py
federated_language/context_stack/symbol_binding_context.py
federated_language/executor/__init__.py
federated_language/executor/async_execution_context.py
federated_language/executor/cardinalities_utils.py
federated_language/executor/executor_base.py
federated_language/executor/executor_factory.py
federated_language/executor/executor_value_base.py
federated_language/executor/sync_execution_context.py
federated_language/federated_context/__init__.py
federated_language/federated_context/federated_computation.py
federated_language/federated_context/federated_computation_context.py
federated_language-0.5.2.dist-info/licenses/LICENSE
federated_language-0.5.2.dist-info/METADATA
federated_language-0.5.2.dist-info/WHEEL
federated_language-0.5.2.dist-info/top_level.txt
federated_language-0.5.2.dist-info/RECORD
