Metadata-Version: 2.4
Name: federated_language
Version: 0.5.2
Summary: A framework for implementing federated algorithms and computations on privacy-sensitive data.
Author-email: Federated Language Team <no-reply@google.com>
License: 
Project-URL: Homepage, https://github.com/google-parfait/federated-language
Project-URL: Issues, https://github.com/google-parfait/federated-language/issues
Project-URL: Releases, https://github.com/google-parfait/federated-language/releases
Keywords: federated,machine,learning
Classifier: Development Status :: 5 - Production/Stable
Classifier: Intended Audience :: Developers
Classifier: Intended Audience :: Education
Classifier: Intended Audience :: Science/Research
Classifier: License :: OSI Approved :: Apache Software License
Classifier: Operating System :: POSIX :: Linux
Classifier: Programming Language :: Python :: 3
Classifier: Programming Language :: Python :: 3.9
Classifier: Programming Language :: Python :: 3.10
Classifier: Programming Language :: Python :: 3.11
Classifier: Programming Language :: Python :: 3.12
Classifier: Programming Language :: Python :: 3.13
Classifier: Programming Language :: Python :: 3 :: Only
Classifier: Topic :: Scientific/Engineering
Classifier: Topic :: Scientific/Engineering :: Artificial Intelligence
Classifier: Topic :: Scientific/Engineering :: Mathematics
Classifier: Topic :: Software Development
Classifier: Topic :: Software Development :: Libraries
Classifier: Topic :: Software Development :: Libraries :: Python Modules
Requires-Python: <3.14,>=3.9
License-File: LICENSE
Requires-Dist: absl-py~=1.0
Requires-Dist: attrs~=23.1
Requires-Dist: dm-tree~=0.1.8
Requires-Dist: ml_dtypes<0.6,>=0.4.0
Requires-Dist: numpy~=2.0
Requires-Dist: protobuf~=5.29
Requires-Dist: typing-extensions~=4.5
Dynamic: license-file
